saga_framework/__init__.py
saga_framework/async_saga.py
saga_framework/asyncapi_utils.py
saga_framework/base_saga.py
saga_framework/celery_utils.py
saga_framework/saga_handlers.py
saga_framework/stateful_saga.py
saga_framework/utils.py
saga_framework-0.1.dist-info/METADATA
saga_framework-0.1.dist-info/WHEEL
saga_framework-0.1.dist-info/top_level.txt
saga_framework-0.1.dist-info/RECORD
