Metadata-Version: 2.1
Name: saga-framework
Version: 0.1
Summary: Mini-framework that helps implementing Saga pattern in microservices
Home-page: https://github.com/absent1706/saga-framework
Author: Alexander Litvinenko
Author-email: litvinenko1706@gmail.com
License: MIT
Download-URL: https://github.com/absent1706/saga-framework/archive/master.tar.gz
Keywords: microservices,saga
Platform: UNKNOWN
Classifier: Development Status :: 4 - Beta
Classifier: Environment :: Web Environment
Classifier: Intended Audience :: Developers
Classifier: License :: OSI Approved :: MIT License
Classifier: Programming Language :: Python :: 3
Requires-Dist: celery
Requires-Dist: asyncapi
